{
  "unversionedId": "why-prettier",
  "id": "why-prettier",
  "title": "Why Prettier?",
  "description": "Building and enforcing a style guide",
  "source": "@site/../docs/why-prettier.md",
  "sourceDirName": ".",
  "slug": "/why-prettier",
  "permalink": "/docs/next/why-prettier",
  "editUrl": "https://github.com/prettier/prettier/edit/main/docs/../docs/why-prettier.md",
  "tags": [],
  "version": "current",
  "lastUpdatedBy": "Simon Lydell",
  "lastUpdatedAt": 1593308849,
  "formattedLastUpdatedAt": "6/28/2020",
  "frontMatter": {
    "id": "why-prettier",
    "title": "Why Prettier?"
  },
  "sidebar": "docs",
  "previous": {
    "title": "What is Prettier?",
    "permalink": "/docs/next/"
  },
  "next": {
    "title": "Prettier vs. Linters",
    "permalink": "/docs/next/comparison"
  }
}